README.rst
doitcmd.py
setup.py
doit_cmd.egg-info/PKG-INFO
doit_cmd.egg-info/SOURCES.txt
doit_cmd.egg-info/dependency_links.txt
doit_cmd.egg-info/requires.txt
doit_cmd.egg-info/top_level.txt