Metadata-Version: 1.1
Name: doit-cmd
Version: 0.1.0
Summary: Helper to create doit tasks that execute a command
Home-page: https://github.com/pydoit/doit-cmd/
Author: Eduardo Naufel Schettino
Author-email: schettino72@gmail.com
License: MIT
Keywords: doit
Platform: any
Classifier: Development Status :: 4 - Beta
Classifier: Intended Audience :: Developers
Classifier: License :: OSI Approved :: MIT License
Classifier: Natural Language :: English
Classifier: Operating System :: OS Independent
Classifier: Programming Language :: Python
Classifier: Programming Language :: Python :: 3
Classifier: Programming Language :: Python :: 3.3
Classifier: Programming Language :: Python :: 3.4
Classifier: Topic :: Software Development :: Libraries
Classifier: Topic :: Software Development :: Libraries :: Python Modules
